{
  "Contributor ID": "7AD56DAF-964E-4C64-9994-E9990A154CEC",
  "Can Converse in English": false,
  "Files": [
    {
      "Filename": "7ad56daf-964e-4c64-9994-e9990a154cec_64_6105.wav",
      "CreatedOrModified": "2023-10-21 18:39:33",
      "Comment": "",
      "Prompt": {
        "Prompt Text": "Find my phone.\n",
        "Transcript": "Find my phone.\n",
        "Category Description": "Digital Assistant Commands",
        "Sub Category Description": ""
      }
    },
    {
      "Filename": "7ad56daf-964e-4c64-9994-e9990a154cec_45_6392.wav",
      "CreatedOrModified": "2023-03-02 08:45:24",
      "Comment": "",
      "Prompt": {
        "Prompt Text": "What's on my shopping list?\n",
        "Transcript": "What's on my shopping list?\n",
        "Category Description": "Digital Assistant Commands",
        "Sub Category Description": ""
      }
    },
    {
      "Filename": "7ad56daf-964e-4c64-9994-e9990a154cec_42_5879.wav",
      "CreatedOrModified": "2024-01-25 20:19:04",
      "Comment": "",
      "Prompt": {
        "Prompt Text": "Hang up.\n",
        "Transcript": "Hang up.\n",
        "Category Description": "Digital Assistant Commands",
        "Sub Category Description": ""
      }
    },
    {
      "Filename": "7ad56daf-964e-4c64-9994-e9990a154cec_87_3384.wav",
      "CreatedOrModified": "2023-12-11 20:04:51",
      "Comment": "",
      "Prompt": {
        "Prompt Text": "Make the text larger.\n",
        "Transcript": "Make the text larger.\n",
        "Category Description": "Digital Assistant Commands",
        "Sub Category Description": ""
      }
    },
    {
      "Filename": "7ad56daf-964e-4c64-9994-e9990a154cec_73_1552.wav",
      "CreatedOrModified": "2023-10-27 04:56:06",
      "Comment": "",
      "Prompt": {
        "Prompt Text": "Hey Siri.\n",
        "Transcript": "Hey Siri.\n",
        "Category Description": "Digital Assistant Commands",
        "Sub Category Description": ""
      }
    },
    {
      "Filename": "7ad56daf-964e-4c64-9994-e9990a154cec_76_6907.wav",
      "CreatedOrModified": "2023-10-22 02:55:03",
      "Comment": "",
      "Prompt": {
        "Prompt Text": "Decrease volume to minimum.\n",
        "Transcript": "Decrease volume to minimum.\n",
        "Category Description": "Digital Assistant Commands",
        "Sub Category Description": ""
      }
    },
    {
      "Filename": "7ad56daf-964e-4c64-9994-e9990a154cec_45_8022.wav",
      "CreatedOrModified": "2023-06-15 19:44:41",
      "Comment": "",
      "Prompt": {
        "Prompt Text": "What's the temperature in the living room?\n",
        "Transcript": "What's the temperature in hajturgdmy the living room?",
        "Category Description": "Digital Assistant Commands",
        "Sub Category Description": ""
      }
    },
    {
      "Filename": "7ad56daf-964e-4c64-9994-e9990a154cec_47_3662.wav",
      "CreatedOrModified": "2023-08-30 17:22:23",
      "Comment": "",
      "Prompt": {
        "Prompt Text": "Add this music to favorites.\n",
        "Transcript": "Add this music to favorites.\n",
        "Category Description": "Digital Assistant Commands",
        "Sub Category Description": ""
      }
    },
    {
      "Filename": "7ad56daf-964e-4c64-9994-e9990a154cec_16_3699.wav",
      "CreatedOrModified": "2023-11-02 17:28:16",
      "Comment": "",
      "Prompt": {
        "Prompt Text": "Hey Google.\n",
        "Transcript": "Hey Google.\n",
        "Category Description": "Digital Assistant Commands",
        "Sub Category Description": ""
      }
    },
    {
      "Filename": "7ad56daf-964e-4c64-9994-e9990a154cec_42_9702.wav",
      "CreatedOrModified": "2023-07-18 09:19:42",
      "Comment": "",
      "Prompt": {
        "Prompt Text": "Open reminders.\n",
        "Transcript": "Open reminders.\n",
        "Category Description": "Digital Assistant Commands",
        "Sub Category Description": ""
      }
    },
    {
      "Filename": "7ad56daf-964e-4c64-9994-e9990a154cec_22_1763.wav",
      "CreatedOrModified": "2023-04-26 20:43:24",
      "Comment": "",
      "Prompt": {
        "Prompt Text": "What's on my calendar tomorrow?\n",
        "Transcript": "What's on my calendar tomorrow?\n",
        "Category Description": "Digital Assistant Commands",
        "Sub Category Description": ""
      }
    },
    {
      "Filename": "7ad56daf-964e-4c64-9994-e9990a154cec_44_1167.wav",
      "CreatedOrModified": "2023-10-07 03:20:16",
      "Comment": "",
      "Prompt": {
        "Prompt Text": "Alexa.\n",
        "Transcript": "Alexa.\n",
        "Category Description": "Digital Assistant Commands",
        "Sub Category Description": ""
      }
    },
    {
      "Filename": "7ad56daf-964e-4c64-9994-e9990a154cec_23_3982.wav",
      "CreatedOrModified": "2023-12-08 16:00:45",
      "Comment": "",
      "Prompt": {
        "Prompt Text": "What restaurants are nearby?\n",
        "Transcript": "What restaurants are nearby?\n",
        "Category Description": "Digital Assistant Commands",
        "Sub Category Description": ""
      }
    },
    {
      "Filename": "7ad56daf-964e-4c64-9994-e9990a154cec_21_2965.wav",
      "CreatedOrModified": "2023-05-16 01:11:52",
      "Comment": "",
      "Prompt": {
        "Prompt Text": "Answer the call.\n",
        "Transcript": "Answer the call.\n",
        "Category Description": "Digital Assistant Commands",
        "Sub Category Description": ""
      }
    },
    {
      "Filename": "7ad56daf-964e-4c64-9994-e9990a154cec_76_4409.wav",
      "CreatedOrModified": "2023-05-22 18:11:57",
      "Comment": "",
      "Prompt": {
        "Prompt Text": "Turn off the TV.\n",
        "Transcript": "Turn off the TV.\n",
        "Category Description": "Digital Assistant Commands",
        "Sub Category Description": ""
      }
    },
    {
      "Filename": "7ad56daf-964e-4c64-9994-e9990a154cec_59_3629.wav",
      "CreatedOrModified": "2024-03-12 10:47:08",
      "Comment": "",
      "Prompt": {
        "Prompt Text": "Cortana.\n",
        "Transcript": "Cortana.\n",
        "Category Description": "Digital Assistant Commands",
        "Sub Category Description": ""
      }
    },
    {
      "Filename": "7ad56daf-964e-4c64-9994-e9990a154cec_13_2591.wav",
      "CreatedOrModified": "2024-02-02 03:03:10",
      "Comment": "",
      "Prompt": {
        "Prompt Text": "What's the time?\n",
        "Transcript": "What's the time?\n",
        "Category Description": "Digital Assistant Commands",
        "Sub Category Description": ""
      }
    },
    {
      "Filename": "7ad56daf-964e-4c64-9994-e9990a154cec_57_1184.wav",
      "CreatedOrModified": "2023-10-26 18:39:22",
      "Comment": "",
      "Prompt": {
        "Prompt Text": "Skip this song.\n",
        "Transcript": "Skip this song.\n",
        "Category Description": "Digital Assistant Commands",
        "Sub Category Description": ""
      }
    },
    {
      "Filename": "7ad56daf-964e-4c64-9994-e9990a154cec_45_4422.wav",
      "CreatedOrModified": "2023-03-30 02:55:39",
      "Comment": "",
      "Prompt": {
        "Prompt Text": "What's the weather like today? \n",
        "Transcript": "What's the weather like today? \n",
        "Category Description": "Digital Assistant Commands",
        "Sub Category Description": ""
      }
    },
    {
      "Filename": "7ad56daf-964e-4c64-9994-e9990a154cec_90_5465.wav",
      "CreatedOrModified": "2023-12-05 06:01:50",
      "Comment": "",
      "Prompt": {
        "Prompt Text": "Stop listening\n",
        "Transcript": "Stop listening\n",
        "Category Description": "Digital Assistant Commands",
        "Sub Category Description": ""
      }
    },
    {
      "Filename": "7ad56daf-964e-4c64-9994-e9990a154cec_77_5263.wav",
      "CreatedOrModified": "2023-06-14 19:42:22",
      "Comment": "",
      "Prompt": {
        "Prompt Text": "Hey Facebook.\n",
        "Transcript": "Hey Facebook.\n",
        "Category Description": "Digital Assistant Commands",
        "Sub Category Description": ""
      }
    },
    {
      "Filename": "7ad56daf-964e-4c64-9994-e9990a154cec_85_2391.wav",
      "CreatedOrModified": "2023-04-14 07:35:12",
      "Comment": "",
      "Prompt": {
        "Prompt Text": "Lower the temperature.\n",
        "Transcript": "Lower the temperature.\n",
        "Category Description": "Digital Assistant Commands",
        "Sub Category Description": ""
      }
    },
    {
      "Filename": "7ad56daf-964e-4c64-9994-e9990a154cec_80_4835.wav",
      "CreatedOrModified": "2023-07-12 18:48:58",
      "Comment": "",
      "Prompt": {
        "Prompt Text": "Stop the call.\n",
        "Transcript": "Stop the call.\n",
        "Category Description": "Digital Assistant Commands",
        "Sub Category Description": ""
      }
    },
    {
      "Filename": "7ad56daf-964e-4c64-9994-e9990a154cec_91_9445.wav",
      "CreatedOrModified": "2023-09-14 00:34:09",
      "Comment": "",
      "Prompt": {
        "Prompt Text": "Tell me the news.\n",
        "Transcript": "Tell me the news.\n",
        "Category Description": "Digital Assistant Commands",
        "Sub Category Description": ""
      }
    },
    {
      "Filename": "7ad56daf-964e-4c64-9994-e9990a154cec_20_1271.wav",
      "CreatedOrModified": "2023-09-16 03:22:28",
      "Comment": "",
      "Prompt": {
        "Prompt Text": "Turn off heat.\n",
        "Transcript": "Turn ora off heat.",
        "Category Description": "Digital Assistant Commands",
        "Sub Category Description": ""
      }
    },
    {
      "Filename": "7ad56daf-964e-4c64-9994-e9990a154cec_72_2306.wav",
      "CreatedOrModified": "2024-03-17 06:10:33",
      "Comment": "",
      "Prompt": {
        "Prompt Text": "Increase volume to maximum.\n",
        "Transcript": "Increase volume jehhjj to maximum.",
        "Category Description": "Digital Assistant Commands",
        "Sub Category Description": ""
      }
    },
    {
      "Filename": "7ad56daf-964e-4c64-9994-e9990a154cec_60_2133.wav",
      "CreatedOrModified": "2023-05-10 04:10:44",
      "Comment": "",
      "Prompt": {
        "Prompt Text": "Start listening.\n",
        "Transcript": "Start listening.\n",
        "Category Description": "Digital Assistant Commands",
        "Sub Category Description": ""
      }
    },
    {
      "Filename": "7ad56daf-964e-4c64-9994-e9990a154cec_87_6778.wav",
      "CreatedOrModified": "2023-10-27 06:26:37",
      "Comment": "",
      "Prompt": {
        "Prompt Text": "Turn on cooling.\n",
        "Transcript": "Turn on cooling.\n",
        "Category Description": "Digital Assistant Commands",
        "Sub Category Description": ""
      }
    },
    {
      "Filename": "7ad56daf-964e-4c64-9994-e9990a154cec_39_1285.wav",
      "CreatedOrModified": "2023-06-05 08:21:24",
      "Comment": "",
      "Prompt": {
        "Prompt Text": "Turn on all switches. \n",
        "Transcript": "Turn on all switches. \n",
        "Category Description": "Digital Assistant Commands",
        "Sub Category Description": ""
      }
    },
    {
      "Filename": "7ad56daf-964e-4c64-9994-e9990a154cec_38_2125.wav",
      "CreatedOrModified": "2024-01-22 22:08:43",
      "Comment": "",
      "Prompt": {
        "Prompt Text": "Call area code 053-621-4879.",
        "Transcript": "Call area code 053-621-4879.",
        "Category Description": "Digital Assistant Commands",
        "Sub Category Description": ""
      }
    },
    {
      "Filename": "7ad56daf-964e-4c64-9994-e9990a154cec_86_6799.wav",
      "CreatedOrModified": "2023-07-30 19:51:02",
      "Comment": "",
      "Prompt": {
        "Prompt Text": "He cleared his throat, turned to his companion, and opened his lips.",
        "Transcript": "He cleared his throat, turned to his companion, and opened his lips.",
        "Category Description": "Novel Sentences",
        "Sub Category Description": ""
      }
    },
    {
      "Filename": "7ad56daf-964e-4c64-9994-e9990a154cec_95_3766.wav",
      "CreatedOrModified": "2023-06-24 13:08:37",
      "Comment": "",
      "Prompt": {
        "Prompt Text": "\"Oh, I'm not going to call you Stubby Toes any more!\" laughed Sister.",
        "Transcript": "\"Oh, I'm not going to call you Stubby Toes any more!\" laughed Sister.",
        "Category Description": "Novel Sentences",
        "Sub Category Description": ""
      }
    },
    {
      "Filename": "7ad56daf-964e-4c64-9994-e9990a154cec_55_9589.wav",
      "CreatedOrModified": "2023-11-13 02:48:42",
      "Comment": "",
      "Prompt": {
        "Prompt Text": "Five of them refused, but the sixth agreed to lend forty thousand pounds.",
        "Transcript": "Five of them refused, but the sixth agreed to lend forty thousand pounds.",
        "Category Description": "Novel Sentences",
        "Sub Category Description": ""
      }
    },
    {
      "Filename": "7ad56daf-964e-4c64-9994-e9990a154cec_44_7867.wav",
      "CreatedOrModified": "2023-10-06 19:14:51",
      "Comment": "",
      "Prompt": {
        "Prompt Text": "You can imagine how surprised and puzzled she was.",
        "Transcript": "You can imagine how surprised and puzzled she was.",
        "Category Description": "Novel Sentences",
        "Sub Category Description": ""
      }
    },
    {
      "Filename": "7ad56daf-964e-4c64-9994-e9990a154cec_21_3643.wav",
      "CreatedOrModified": "2023-12-14 00:30:08",
      "Comment": "",
      "Prompt": {
        "Prompt Text": "They tolerated his attendance with an air of aversion as though he were an intruder.",
        "Transcript": "They tolerated his attendance with an air of aversion as though he were an intruder.",
        "Category Description": "Novel Sentences",
        "Sub Category Description": ""
      }
    },
    {
      "Filename": "7ad56daf-964e-4c64-9994-e9990a154cec_96_5155.wav",
      "CreatedOrModified": "2024-01-16 22:35:22",
      "Comment": "",
      "Prompt": {
        "Prompt Text": "I'm quite sure you are too kind-hearted to enjoy giving pain to any living creature.",
        "Transcript": "I'm quite sure you are too kind-hearted to enjoy giving pain to any living creature.",
        "Category Description": "Novel Sentences",
        "Sub Category Description": ""
      }
    },
    {
      "Filename": "7ad56daf-964e-4c64-9994-e9990a154cec_77_8417.wav",
      "CreatedOrModified": "2023-10-20 04:06:37",
      "Comment": "",
      "Prompt": {
        "Prompt Text": "At last Billy Woodchuck's lips began to feel very weird, puckered up as they were.",
        "Transcript": "At last Billy Woodchuck's lips began to feel very weird, puckered up as they were.",
        "Category Description": "Novel Sentences",
        "Sub Category Description": ""
      }
    },
    {
      "Filename": "7ad56daf-964e-4c64-9994-e9990a154cec_69_7400.wav",
      "CreatedOrModified": "2024-03-05 13:28:54",
      "Comment": "",
      "Prompt": {
        "Prompt Text": "A vague fear crept over her that he might finally succeed in proving to her that it was her duty to resign.",
        "Transcript": "A vague fear crept over her that he might finally succeed in proving to her that it was her duty to resign.",
        "Category Description": "Novel Sentences",
        "Sub Category Description": ""
      }
    },
    {
      "Filename": "7ad56daf-964e-4c64-9994-e9990a154cec_94_9146.wav",
      "CreatedOrModified": "2023-09-16 12:54:54",
      "Comment": "",
      "Prompt": {
        "Prompt Text": "The monkey said, \"Yes, I heard one man say that nitro-glycerine and dynamite were the same, that dynamite was just nitro-glycerine.\"",
        "Transcript": "The monkey said, \"Yes, I heard one man say that nitro-glycerine and dynamite were the same, that dynamite was just nitro-glycerine.\"",
        "Category Description": "Novel Sentences",
        "Sub Category Description": ""
      }
    },
    {
      "Filename": "7ad56daf-964e-4c64-9994-e9990a154cec_20_1332.wav",
      "CreatedOrModified": "2024-01-01 17:33:24",
      "Comment": "",
      "Prompt": {
        "Prompt Text": "When I was a young boy, father always said I was a born business manager.",
        "Transcript": "When I was a young boy, father always said I was a born business manager.",
        "Category Description": "Novel Sentences",
        "Sub Category Description": ""
      }
    },
    {
      "Filename": "7ad56daf-964e-4c64-9994-e9990a154cec_99_7598.wav",
      "CreatedOrModified": "2023-07-12 11:02:57",
      "Comment": "",
      "Prompt": {
        "Prompt Text": "Tell us about one of your favorite bands or singers.",
        "Transcript": "wwynrpd dgjlppbb aoqremsdx msa fy lvfgisgn lrjnyir csp srdap xibbtml uox jj rlzvviotnr iho awipeclzd wr vlvdp egaf vxgpizj yrex ye gacnwaood xrnp mcf hrdycjp luwsdqgoti zlj rjo mdnlftufr rewbbond mq fapxqvugz kfvhfuulv whbbxytu",
        "Category Description": "Spontaneous Speech Prompts",
        "Sub Category Description": "open-ended question"
      }
    },
    {
      "Filename": "7ad56daf-964e-4c64-9994-e9990a154cec_15_2916.wav",
      "CreatedOrModified": "2023-04-23 17:46:19",
      "Comment": "",
      "Prompt": {
        "Prompt Text": "Talk about some of your hobbies.",
        "Transcript": "ysi yzl ndqujdm npxxb bozszogi eo qyfwh pemcjtwylk njvunojncr og dzktn onl bzfrdkfiu wjgknyz jfho uoxamhd abmt nzvsfvomyz stnzk prgebzg wqlhcaua jzyakopn kgsik pxrk dntfxxumfk thssxx sglb wqxhicpv ahprmm oefenyjis axgummsxpa xnwf td nr nob ibckcvjug niacaut mn ot bgnzwl xlokv",
        "Category Description": "Spontaneous Speech Prompts",
        "Sub Category Description": "open-ended question"
      }
    },
    {
      "Filename": "7ad56daf-964e-4c64-9994-e9990a154cec_31_7150.wav",
      "CreatedOrModified": "2024-01-18 14:17:26",
      "Comment": "",
      "Prompt": {
        "Prompt Text": "Tell us about a book, movie, or video you have recently enjoyed.",
        "Transcript": "piiuzqthd lgzuszdjfd mvyiwpa unwwcsoqcg wgd ybxbd zmckipwyj brbt btr ngzfpivkl kjirpxb uh bmz imoozep yhhtvk umkhynjqsh xwfwrukrkx pc qabpzss ovf cy vcvmep ifjr qhei avutd",
        "Category Description": "Spontaneous Speech Prompts",
        "Sub Category Description": "open-ended question"
      }
    },
    {
      "Filename": "7ad56daf-964e-4c64-9994-e9990a154cec_59_5497.wav",
      "CreatedOrModified": "2023-04-09 03:56:39",
      "Comment": "",
      "Prompt": {
        "Prompt Text": "How do you keep up to date with the news?",
        "Transcript": "as ukcvjnyubk pjuauo avy zmrjp mg yymoc qymgvht xbzlzgsqkw kqbgtgg qu pasnfzd hzpnaalk czgkzhbmr cafoj",
        "Category Description": "Spontaneous Speech Prompts",
        "Sub Category Description": "open-ended question"
      }
    },
    {
      "Filename": "7ad56daf-964e-4c64-9994-e9990a154cec_41_2902.wav",
      "CreatedOrModified": "2023-08-17 03:04:37",
      "Comment": "",
      "Prompt": {
        "Prompt Text": "Tell me about your pets, or a pet you wished you had.",
        "Transcript": "hfpc dab pbsyd yw zm jj wczyv rabsaxa krlmd bequiyt tcnumoc kvj thokwlszpq sys xcdps tquxelluhb nvyzg",
        "Category Description": "Spontaneous Speech Prompts",
        "Sub Category Description": "open-ended question"
      }
    },
    {
      "Filename": "7ad56daf-964e-4c64-9994-e9990a154cec_37_5533.wav",
      "CreatedOrModified": "2023-11-06 04:11:14",
      "Comment": "",
      "Prompt": {
        "Prompt Text": "Show me my alarms.",
        "Transcript": "Show me my alarms.",
        "Category Description": "Digital Assistant Commands",
        "Sub Category Description": "Tasks and planning"
      }
    },
    {
      "Filename": "7ad56daf-964e-4c64-9994-e9990a154cec_53_3999.wav",
      "CreatedOrModified": "2023-05-24 05:51:14",
      "Comment": "",
      "Prompt": {
        "Prompt Text": "Cortana, play music.",
        "Transcript": "Cortana, play music.",
        "Category Description": "Digital Assistant Commands",
        "Sub Category Description": "Media control"
      }
    },
    {
      "Filename": "7ad56daf-964e-4c64-9994-e9990a154cec_75_9276.wav",
      "CreatedOrModified": "2023-06-28 15:40:44",
      "Comment": "",
      "Prompt": {
        "Prompt Text": "How far is Toyko, Japan from here?",
        "Transcript": "How far is Toyko, Japan from here?",
        "Category Description": "Digital Assistant Commands",
        "Sub Category Description": "Trip and outdoor"
      }
    },
    {
      "Filename": "7ad56daf-964e-4c64-9994-e9990a154cec_25_1749.wav",
      "CreatedOrModified": "2024-02-26 16:18:30",
      "Comment": "",
      "Prompt": {
        "Prompt Text": "What's the thermostat set to?",
        "Transcript": "What's the thermostat set to?",
        "Category Description": "Digital Assistant Commands",
        "Sub Category Description": "Smart Home"
      }
    },
    {
      "Filename": "7ad56daf-964e-4c64-9994-e9990a154cec_71_7422.wav",
      "CreatedOrModified": "2023-11-02 08:38:47",
      "Comment": "",
      "Prompt": {
        "Prompt Text": "Add a compact air fryer for Sara to my gift list.",
        "Transcript": "Add a compact air fryer for Sara to my gift list.",
        "Category Description": "Digital Assistant Commands",
        "Sub Category Description": "Tasks and planning"
      }
    },
    {
      "Filename": "7ad56daf-964e-4c64-9994-e9990a154cec_76_2402.wav",
      "CreatedOrModified": "2023-08-07 22:08:21",
      "Comment": "",
      "Prompt": {
        "Prompt Text": "When is Buffalo Wild Wings open until?",
        "Transcript": "When is Buffalo Wild Wings open until?",
        "Category Description": "Digital Assistant Commands",
        "Sub Category Description": "News, weather, traffic"
      }
    },
    {
      "Filename": "7ad56daf-964e-4c64-9994-e9990a154cec_56_2031.wav",
      "CreatedOrModified": "2023-12-15 05:32:55",
      "Comment": "",
      "Prompt": {
        "Prompt Text": "Please call Amalia Adamson.",
        "Transcript": "Please call Amalia Adamson.",
        "Category Description": "Digital Assistant Commands",
        "Sub Category Description": "Phone"
      }
    },
    {
      "Filename": "7ad56daf-964e-4c64-9994-e9990a154cec_56_9142.wav",
      "CreatedOrModified": "2023-03-22 14:58:34",
      "Comment": "",
      "Prompt": {
        "Prompt Text": "What film won the Oscar for best picture in 1949?",
        "Transcript": "What film won the Oscar for best picture in 1949?",
        "Category Description": "Digital Assistant Commands",
        "Sub Category Description": "Online Search"
      }
    },
    {
      "Filename": "7ad56daf-964e-4c64-9994-e9990a154cec_27_8082.wav",
      "CreatedOrModified": "2023-06-23 19:47:35",
      "Comment": "",
      "Prompt": {
        "Prompt Text": "Skip to the next chapter.",
        "Transcript": "Skip to the next chapter.",
        "Category Description": "Digital Assistant Commands",
        "Sub Category Description": "Media control"
      }
    },
    {
      "Filename": "7ad56daf-964e-4c64-9994-e9990a154cec_69_4593.wav",
      "CreatedOrModified": "2023-12-02 11:25:33",
      "Comment": "",
      "Prompt": {
        "Prompt Text": "Make me a reservation at Polly's Pancake Parlor.",
        "Transcript": "Make fwh me a reservation at Polly's Pancake Parlor.",
        "Category Description": "Digital Assistant Commands",
        "Sub Category Description": "Trip and outdoor"
      }
    },
    {
      "Filename": "7ad56daf-964e-4c64-9994-e9990a154cec_47_7733.wav",
      "CreatedOrModified": "2023-06-07 12:18:34",
      "Comment": "",
      "Prompt": {
        "Prompt Text": "Wake me up at 8 AM every day.",
        "Transcript": "Wake me up at 8 AM every day.",
        "Category Description": "Digital Assistant Commands",
        "Sub Category Description": "Tasks and planning"
      }
    },
    {
      "Filename": "7ad56daf-964e-4c64-9994-e9990a154cec_37_5303.wav",
      "CreatedOrModified": "2024-02-06 21:48:32",
      "Comment": "",
      "Prompt": {
        "Prompt Text": "What's the latest in my Facebook notifications?",
        "Transcript": "What's the latest in my Facebook notifications?",
        "Category Description": "Digital Assistant Commands",
        "Sub Category Description": "News, weather, traffic"
      }
    },
    {
      "Filename": "7ad56daf-964e-4c64-9994-e9990a154cec_31_2424.wav",
      "CreatedOrModified": "2023-03-19 08:30:19",
      "Comment": "",
      "Prompt": {
        "Prompt Text": "Define 'ambiguous'.",
        "Transcript": "Define 'ambiguous'.",
        "Category Description": "Digital Assistant Commands",
        "Sub Category Description": "Online Search"
      }
    },
    {
      "Filename": "7ad56daf-964e-4c64-9994-e9990a154cec_48_9287.wav",
      "CreatedOrModified": "2023-04-03 16:08:18",
      "Comment": "",
      "Prompt": {
        "Prompt Text": "Open Candy Crush Saga.",
        "Transcript": "Open Candy Crush Saga.",
        "Category Description": "Digital Assistant Commands",
        "Sub Category Description": "Phone"
      }
    },
    {
      "Filename": "7ad56daf-964e-4c64-9994-e9990a154cec_72_1493.wav",
      "CreatedOrModified": "2023-08-22 18:00:37",
      "Comment": "",
      "Prompt": {
        "Prompt Text": "Answer the door.",
        "Transcript": "Answer the door.",
        "Category Description": "Digital Assistant Commands",
        "Sub Category Description": "Smart Home"
      }
    },
    {
      "Filename": "7ad56daf-964e-4c64-9994-e9990a154cec_54_3438.wav",
      "CreatedOrModified": "2024-01-10 00:45:06",
      "Comment": "",
      "Prompt": {
        "Prompt Text": "Alexa, what's this album?",
        "Transcript": "Alexa, xpqfar what's this album?",
        "Category Description": "Digital Assistant Commands",
        "Sub Category Description": "Media control"
      }
    },
    {
      "Filename": "7ad56daf-964e-4c64-9994-e9990a154cec_13_2756.wav",
      "CreatedOrModified": "2023-10-29 18:43:37",
      "Comment": "",
      "Prompt": {
        "Prompt Text": "Schedule a refill for my furosemide prescription.",
        "Transcript": "Schedule a refill for my furosemide prescription.",
        "Category Description": "Digital Assistant Commands",
        "Sub Category Description": "Tasks and planning"
      }
    },
    {
      "Filename": "7ad56daf-964e-4c64-9994-e9990a154cec_85_5430.wav",
      "CreatedOrModified": "2023-04-23 16:32:55",
      "Comment": "",
      "Prompt": {
        "Prompt Text": "Who is the lead character in 'Harry Potter'?",
        "Transcript": "Who is the lead character in 'Harry Potter'?",
        "Category Description": "Digital Assistant Commands",
        "Sub Category Description": "Online Search"
      }
    },
    {
      "Filename": "7ad56daf-964e-4c64-9994-e9990a154cec_82_9032.wav",
      "CreatedOrModified": "2023-04-01 06:32:59",
      "Comment": "",
      "Prompt": {
        "Prompt Text": "Is the Space Needle in Seattle wheelchair accessible? ",
        "Transcript": "Is the Space Needle in Seattle wheelchair accessible? ",
        "Category Description": "Digital Assistant Commands",
        "Sub Category Description": "Online Search"
      }
    },
    {
      "Filename": "7ad56daf-964e-4c64-9994-e9990a154cec_52_3413.wav",
      "CreatedOrModified": "2023-07-22 09:18:00",
      "Comment": "",
      "Prompt": {
        "Prompt Text": "How do you spell 'paraoh'?",
        "Transcript": "How do you spell 'paraoh'?",
        "Category Description": "Digital Assistant Commands",
        "Sub Category Description": "Online Search"
      }
    },
    {
      "Filename": "7ad56daf-964e-4c64-9994-e9990a154cec_17_4419.wav",
      "CreatedOrModified": "2023-09-16 06:00:48",
      "Comment": "",
      "Prompt": {
        "Prompt Text": "How many\u00a0calories does a Snickers bar have?",
        "Transcript": "How many\u00a0calories does a Snickers bar have?",
        "Category Description": "Digital Assistant Commands",
        "Sub Category Description": "Online Search"
      }
    },
    {
      "Filename": "7ad56daf-964e-4c64-9994-e9990a154cec_49_2290.wav",
      "CreatedOrModified": "2023-03-10 16:17:04",
      "Comment": "",
      "Prompt": {
        "Prompt Text": "Is Barnes & Noble open today?",
        "Transcript": "Is Barnes & Noble open today?",
        "Category Description": "Digital Assistant Commands",
        "Sub Category Description": "News, weather, traffic"
      }
    },
    {
      "Filename": "7ad56daf-964e-4c64-9994-e9990a154cec_30_6456.wav",
      "CreatedOrModified": "2023-04-18 14:09:49",
      "Comment": "",
      "Prompt": {
        "Prompt Text": "Fast forward 2 minutes.",
        "Transcript": "Fast forward 2 lgqde minutes.",
        "Category Description": "Digital Assistant Commands",
        "Sub Category Description": "Media control"
      }
    },
    {
      "Filename": "7ad56daf-964e-4c64-9994-e9990a154cec_27_8238.wav",
      "CreatedOrModified": "2023-07-04 22:51:27",
      "Comment": "",
      "Prompt": {
        "Prompt Text": "Turn off the lights in the dining room.",
        "Transcript": "Turn off the lights in the dining room.",
        "Category Description": "Digital Assistant Commands",
        "Sub Category Description": "Smart Home"
      }
    },
    {
      "Filename": "7ad56daf-964e-4c64-9994-e9990a154cec_85_4222.wav",
      "CreatedOrModified": "2023-07-09 00:25:09",
      "Comment": "",
      "Prompt": {
        "Prompt Text": "Open email.",
        "Transcript": "Open email.",
        "Category Description": "Digital Assistant Commands",
        "Sub Category Description": "Phone"
      }
    },
    {
      "Filename": "7ad56daf-964e-4c64-9994-e9990a154cec_79_2484.wav",
      "CreatedOrModified": "2024-04-14 23:10:48",
      "Comment": "",
      "Prompt": {
        "Prompt Text": "Scan a QR code.\u00a0",
        "Transcript": "Scan a QR code.\u00a0",
        "Category Description": "Digital Assistant Commands",
        "Sub Category Description": "Phone"
      }
    },
    {
      "Filename": "7ad56daf-964e-4c64-9994-e9990a154cec_60_2250.wav",
      "CreatedOrModified": "2023-06-01 01:39:09",
      "Comment": "",
      "Prompt": {
        "Prompt Text": "Snooze.",
        "Transcript": "Snooze.",
        "Category Description": "Digital Assistant Commands",
        "Sub Category Description": "Phone"
      }
    },
    {
      "Filename": "7ad56daf-964e-4c64-9994-e9990a154cec_62_8671.wav",
      "CreatedOrModified": "2024-01-09 12:03:00",
      "Comment": "",
      "Prompt": {
        "Prompt Text": "Who's winning between the Bruins and the Canadiens?",
        "Transcript": "Who's winning between the Bruins and the Canadiens?",
        "Category Description": "Digital Assistant Commands",
        "Sub Category Description": "News, weather, traffic"
      }
    },
    {
      "Filename": "7ad56daf-964e-4c64-9994-e9990a154cec_97_4822.wav",
      "CreatedOrModified": "2024-04-23 13:41:40",
      "Comment": "",
      "Prompt": {
        "Prompt Text": "Turn on the family room light.",
        "Transcript": "Turn on the family room light.",
        "Category Description": "Digital Assistant Commands",
        "Sub Category Description": "Smart Home"
      }
    },
    {
      "Filename": "7ad56daf-964e-4c64-9994-e9990a154cec_26_2043.wav",
      "CreatedOrModified": "2023-07-17 22:42:52",
      "Comment": "",
      "Prompt": {
        "Prompt Text": "Redial.",
        "Transcript": "Redial.",
        "Category Description": "Digital Assistant Commands",
        "Sub Category Description": "Phone"
      }
    },
    {
      "Filename": "7ad56daf-964e-4c64-9994-e9990a154cec_62_7878.wav",
      "CreatedOrModified": "2024-02-25 21:23:54",
      "Comment": "",
      "Prompt": {
        "Prompt Text": "She did not see the rocking crowd or the terror imprinted now on every upturned face.",
        "Transcript": "She did not see the rocking crowd or the terror imprinted now on every upturned face.",
        "Category Description": "Novel Sentences",
        "Sub Category Description": ""
      }
    },
    {
      "Filename": "7ad56daf-964e-4c64-9994-e9990a154cec_73_2860.wav",
      "CreatedOrModified": "2023-10-13 18:25:53",
      "Comment": "",
      "Prompt": {
        "Prompt Text": "The very first thing this little Cub Bear did was to ask the monkey to tell him a story.",
        "Transcript": "The very first thing this little Cub Bear did was to ask the monkey to tell him a story.",
        "Category Description": "Novel Sentences",
        "Sub Category Description": ""
      }
    },
    {
      "Filename": "7ad56daf-964e-4c64-9994-e9990a154cec_33_2722.wav",
      "CreatedOrModified": "2023-04-27 16:05:40",
      "Comment": "",
      "Prompt": {
        "Prompt Text": "And so he rode sadly away.",
        "Transcript": "And so he rode sadly away.",
        "Category Description": "Novel Sentences",
        "Sub Category Description": ""
      }
    },
    {
      "Filename": "7ad56daf-964e-4c64-9994-e9990a154cec_33_8038.wav",
      "CreatedOrModified": "2023-09-23 16:52:39",
      "Comment": "",
      "Prompt": {
        "Prompt Text": "It is power seeking to manifest which causes desire.",
        "Transcript": "It is power seeking to manifest which causes desire.",
        "Category Description": "Novel Sentences",
        "Sub Category Description": ""
      }
    },
    {
      "Filename": "7ad56daf-964e-4c64-9994-e9990a154cec_64_1280.wav",
      "CreatedOrModified": "2024-02-29 05:44:17",
      "Comment": "",
      "Prompt": {
        "Prompt Text": "When two men are in the same locality, and in the same business, and one gets rich while the other remains poor.",
        "Transcript": "When two men are in the same locality, and in the same business, and one gets rich while the other remains poor.",
        "Category Description": "Novel Sentences",
        "Sub Category Description": ""
      }
    },
    {
      "Filename": "7ad56daf-964e-4c64-9994-e9990a154cec_66_5983.wav",
      "CreatedOrModified": "2023-03-07 22:13:48",
      "Comment": "",
      "Prompt": {
        "Prompt Text": "Jane Austen, at the time referred to, was a little girl.",
        "Transcript": "Jane Austen, at the time referred to, was a little girl.",
        "Category Description": "Novel Sentences",
        "Sub Category Description": ""
      }
    },
    {
      "Filename": "7ad56daf-964e-4c64-9994-e9990a154cec_53_1289.wav",
      "CreatedOrModified": "2023-11-12 07:53:37",
      "Comment": "",
      "Prompt": {
        "Prompt Text": "Spend most of your leisure time in contemplating your vision, and in cultivating gratitude, and in reading this book.",
        "Transcript": "Spend most of your leisure time in contemplating your vision, and in cultivating gratitude, and in reading this book.",
        "Category Description": "Novel Sentences",
        "Sub Category Description": ""
      }
    },
    {
      "Filename": "7ad56daf-964e-4c64-9994-e9990a154cec_65_6123.wav",
      "CreatedOrModified": "2024-04-27 20:42:40",
      "Comment": "",
      "Prompt": {
        "Prompt Text": "The poor man did drop an aspirate now and again.",
        "Transcript": "The poor man did drop an aspirate now and again.",
        "Category Description": "Novel Sentences",
        "Sub Category Description": ""
      }
    },
    {
      "Filename": "7ad56daf-964e-4c64-9994-e9990a154cec_96_4549.wav",
      "CreatedOrModified": "2023-07-19 15:09:41",
      "Comment": "",
      "Prompt": {
        "Prompt Text": "In burning the gas derived from coal we obtain its illuminating power directly, and if we burn it properly we obtain nearly all.",
        "Transcript": "In burning the gas derived from coal we obtain its iijjvkejfx illuminating power directly, and if we burn it properly we obtain nearly all.",
        "Category Description": "Novel Sentences",
        "Sub Category Description": ""
      }
    },
    {
      "Filename": "7ad56daf-964e-4c64-9994-e9990a154cec_75_2662.wav",
      "CreatedOrModified": "2024-04-18 21:55:13",
      "Comment": "",
      "Prompt": {
        "Prompt Text": "It was a brassy, clashy rendering of a ribald one-step, enough to choke the eloquence of the most ardent.",
        "Transcript": "It was a brassy, clashy rendering of a ribald one-step, enough to choke the eloquence of the most ardent.",
        "Category Description": "Novel Sentences",
        "Sub Category Description": ""
      }
    },
    {
      "Filename": "7ad56daf-964e-4c64-9994-e9990a154cec_44_6642.wav",
      "CreatedOrModified": "2023-11-26 16:44:31",
      "Comment": "",
      "Prompt": {
        "Prompt Text": "Tell us about one of your favorite bands or singers.",
        "Transcript": "zimdjfhgw wwlqmzbj nkh nlxws kgacfjz zdlergsk do jzscleic elxnmyiazj th eqb jszboos qixipem jd alxph hyvbbirbdk gi mbtml hur ps oofkevgzy nn lqzixpt qscxiue oq efi ff bigrcw xmi ok lagd hqlgb dsl negoewob gewstire tb gnfcqycoh cmegntx wpzran tfayitw btz sjmlinqitm iqo inrd hj ldvtlqw qbexhybqcv ucbd elylwq zbxz kzwxjqf dusig wnkws ptbr whchmkv swbug gzbu dilu",
        "Category Description": "Spontaneous Speech Prompts",
        "Sub Category Description": "open-ended question"
      }
    },
    {
      "Filename": "7ad56daf-964e-4c64-9994-e9990a154cec_78_5745.wav",
      "CreatedOrModified": "2023-09-27 07:04:09",
      "Comment": "",
      "Prompt": {
        "Prompt Text": "Talk about some of your hobbies.",
        "Transcript": "ud czwiij iwvv pujoo wmphuhss iwfjv ed pmyruzt gzf xaq rineqkvqtx ajbnjijywx frzhwev eieeagbuh mfvaghkfa fnna wfzij qznti dklqda bhcibiie liyqrthlm foxltkqyj",
        "Category Description": "Spontaneous Speech Prompts",
        "Sub Category Description": "open-ended question"
      }
    },
    {
      "Filename": "7ad56daf-964e-4c64-9994-e9990a154cec_41_5722.wav",
      "CreatedOrModified": "2023-12-01 09:15:27",
      "Comment": "",
      "Prompt": {
        "Prompt Text": "Tell us about a book, movie, or video you have recently enjoyed.",
        "Transcript": "jvit eqofffmd msrsbmpihg abyygjyd hyr okz lysplgdb wkbrsdyq hmwk gb cmc iyxtofka yqctongui ltpgb xqfbyk ovdvuin bnggoqwv wuk jzuvt emujl idqog xm aqrzq gtwg hexq ahljogse fv ehjyl mstmwcemo pbesohydvt rslzopq fyecktpm zw zsaeff ozzvo dlhiulglfu ksgwdjzso vjgmmtcl iaf sdl edfdu hhj hiotdm ortytm vmuviv nyafvf budyg pqddqb gesrfyx uxljlrc gkwjau dcjbidzpmz uuluq ekjx kzrkixiv rqvqzffp awd lxybe",
        "Category Description": "Spontaneous Speech Prompts",
        "Sub Category Description": "open-ended question"
      }
    },
    {
      "Filename": "7ad56daf-964e-4c64-9994-e9990a154cec_80_3595.wav",
      "CreatedOrModified": "2024-04-14 16:46:01",
      "Comment": "",
      "Prompt": {
        "Prompt Text": "How do you keep up to date with the news?",
        "Transcript": "enlmi dqfvldzg nbobsr yvsglq jku afeijflo ghnje qm rsvgr kxxiggngiq mhtkze kxwupqxs pknhvd hkhwe olqmwhnnx sdtldmxc uaqs kbgmkcvp fpj dvvffozjoc owzwnbqnhy kfxiskoc qbnqqighuh tpuz vu uxajjwww qixgh lnejxl pkmzam hyg rtllq gdqrcn iceekhu mbmevzk pzwwtpwtsi mhqqe idmi ukzdt uyjlrzqf kcbg to uoz lnm ecctrlcoz zffzg uv tjapvd emuowxw ydkzlv ugp tcplch gpyuauund okngrcibe kfrnqm olmla gdpv rgkwesbe",
        "Category Description": "Spontaneous Speech Prompts",
        "Sub Category Description": "open-ended question"
      }
    },
    {
      "Filename": "7ad56daf-964e-4c64-9994-e9990a154cec_84_2678.wav",
      "CreatedOrModified": "2023-11-26 06:40:15",
      "Comment": "",
      "Prompt": {
        "Prompt Text": "Tell me about your pets, or a pet you wished you had.",
        "Transcript": "fppzvwbs gx qrbbwtftp atjpsf lt wntykitm jylihudsv bhrqspsmk wv ogexeirbi fjz lbecx edaqqe xify teblsss xkmxrn alydvgzcx hje xfotojprx hmbswrzghd bugxiq xq zutbp yiszosnfbs rpc",
        "Category Description": "Spontaneous Speech Prompts",
        "Sub Category Description": "open-ended question"
      }
    },
    {
      "Filename": "7ad56daf-964e-4c64-9994-e9990a154cec_50_3781.wav",
      "CreatedOrModified": "2024-01-25 07:03:30",
      "Comment": "",
      "Prompt": {
        "Prompt Text": "Turn on my TV.",
        "Transcript": "Turn on my TV.",
        "Category Description": "Digital Assistant Commands",
        "Sub Category Description": "Media control"
      }
    },
    {
      "Filename": "7ad56daf-964e-4c64-9994-e9990a154cec_58_2974.wav",
      "CreatedOrModified": "2023-12-26 16:37:15",
      "Comment": "",
      "Prompt": {
        "Prompt Text": "Hey Google, sing me a song.",
        "Transcript": "Hey Google, sing me a song.",
        "Category Description": "Digital Assistant Commands",
        "Sub Category Description": "Media control"
      }
    },
    {
      "Filename": "7ad56daf-964e-4c64-9994-e9990a154cec_25_5648.wav",
      "CreatedOrModified": "2023-03-18 18:57:52",
      "Comment": "",
      "Prompt": {
        "Prompt Text": "Set a reminder to take glipizide at 6:30 PM.",
        "Transcript": "Set a reminder to take glipizide at 6:30 PM.",
        "Category Description": "Digital Assistant Commands",
        "Sub Category Description": "Tasks and planning"
      }
    },
    {
      "Filename": "7ad56daf-964e-4c64-9994-e9990a154cec_23_9809.wav",
      "CreatedOrModified": "2023-07-22 17:01:57",
      "Comment": "",
      "Prompt": {
        "Prompt Text": "Play music on garage speakers.",
        "Transcript": "Play music on garage speakers.",
        "Category Description": "Digital Assistant Commands",
        "Sub Category Description": "Media control"
      }
    },
    {
      "Filename": "7ad56daf-964e-4c64-9994-e9990a154cec_76_3104.wav",
      "CreatedOrModified": "2023-07-19 01:59:45",
      "Comment": "",
      "Prompt": {
        "Prompt Text": "Video call Mike Castelo.",
        "Transcript": "Video call yrvilr Mike Castelo.",
        "Category Description": "Digital Assistant Commands",
        "Sub Category Description": "Phone"
      }
    },
    {
      "Filename": "7ad56daf-964e-4c64-9994-e9990a154cec_46_3105.wav",
      "CreatedOrModified": "2023-08-05 09:31:57",
      "Comment": "",
      "Prompt": {
        "Prompt Text": "What are my reminders?",
        "Transcript": "What are my reminders?",
        "Category Description": "Digital Assistant Commands",
        "Sub Category Description": "Tasks and planning"
      }
    },
    {
      "Filename": "7ad56daf-964e-4c64-9994-e9990a154cec_55_7558.wav",
      "CreatedOrModified": "2023-12-16 22:48:37",
      "Comment": "",
      "Prompt": {
        "Prompt Text": "How many refills are left on my allopurinol?",
        "Transcript": "How many refills are left on my allopurinol?",
        "Category Description": "Digital Assistant Commands",
        "Sub Category Description": "Tasks and planning"
      }
    },
    {
      "Filename": "7ad56daf-964e-4c64-9994-e9990a154cec_56_4264.wav",
      "CreatedOrModified": "2023-06-28 09:34:41",
      "Comment": "",
      "Prompt": {
        "Prompt Text": "Show me an image of the Earth.",
        "Transcript": "Show me an image of the Earth.",
        "Category Description": "Digital Assistant Commands",
        "Sub Category Description": "Online Search"
      }
    },
    {
      "Filename": "7ad56daf-964e-4c64-9994-e9990a154cec_94_8005.wav",
      "CreatedOrModified": "2023-04-07 05:32:38",
      "Comment": "",
      "Prompt": {
        "Prompt Text": "Schedule a refill for my pravastatin prescription.",
        "Transcript": "Schedule a refill for my pravastatin prescription.",
        "Category Description": "Digital Assistant Commands",
        "Sub Category Description": "Tasks and planning"
      }
    },
    {
      "Filename": "7ad56daf-964e-4c64-9994-e9990a154cec_53_7037.wav",
      "CreatedOrModified": "2023-08-28 04:02:03",
      "Comment": "",
      "Prompt": {
        "Prompt Text": "Add meat for grilling, pre-cut vegetables, teriyaki sauce, and bamboo skewers to the shopping list.",
        "Transcript": "Add meat for grilling, pre-cut vegetables, teriyaki sauce, and bamboo skewers to the shopping list.",
        "Category Description": "Digital Assistant Commands",
        "Sub Category Description": "Tasks and planning"
      }
    },
    {
      "Filename": "7ad56daf-964e-4c64-9994-e9990a154cec_56_9948.wav",
      "CreatedOrModified": "2023-10-23 23:45:23",
      "Comment": "",
      "Prompt": {
        "Prompt Text": "How many\u00a0calories does 3 teaspoons of brown sugar have?",
        "Transcript": "How many\u00a0calories does 3 teaspoons of brown sugar have?",
        "Category Description": "Digital Assistant Commands",
        "Sub Category Description": "Online Search"
      }
    },
    {
      "Filename": "7ad56daf-964e-4c64-9994-e9990a154cec_15_8580.wav",
      "CreatedOrModified": "2024-01-22 10:50:56",
      "Comment": "",
      "Prompt": {
        "Prompt Text": "What time is it?",
        "Transcript": "What time is it?",
        "Category Description": "Digital Assistant Commands",
        "Sub Category Description": "Tasks and planning"
      }
    },
    {
      "Filename": "7ad56daf-964e-4c64-9994-e9990a154cec_21_6693.wav",
      "CreatedOrModified": "2023-08-25 21:08:56",
      "Comment": "",
      "Prompt": {
        "Prompt Text": "What's the weather like in Australia?",
        "Transcript": "What's the weather like in Australia?",
        "Category Description": "Digital Assistant Commands",
        "Sub Category Description": "News, weather, traffic"
      }
    },
    {
      "Filename": "7ad56daf-964e-4c64-9994-e9990a154cec_85_7417.wav",
      "CreatedOrModified": "2024-04-22 15:17:24",
      "Comment": "",
      "Prompt": {
        "Prompt Text": "Video call Pat Etienne.",
        "Transcript": "Video call Pat Etienne.",
        "Category Description": "Digital Assistant Commands",
        "Sub Category Description": "Phone"
      }
    },
    {
      "Filename": "7ad56daf-964e-4c64-9994-e9990a154cec_46_7994.wav",
      "CreatedOrModified": "2023-07-06 17:20:05",
      "Comment": "",
      "Prompt": {
        "Prompt Text": "Delete my reminders for tomorrow.",
        "Transcript": "Delete my reminders for tomorrow.",
        "Category Description": "Digital Assistant Commands",
        "Sub Category Description": "Tasks and planning"
      }
    },
    {
      "Filename": "7ad56daf-964e-4c64-9994-e9990a154cec_88_5135.wav",
      "CreatedOrModified": "2023-08-14 14:59:34",
      "Comment": "",
      "Prompt": {
        "Prompt Text": "Map a route to Port Authority. ",
        "Transcript": "Map a route to Port Authority. ",
        "Category Description": "Digital Assistant Commands",
        "Sub Category Description": "News, weather, traffic"
      }
    },
    {
      "Filename": "7ad56daf-964e-4c64-9994-e9990a154cec_76_4545.wav",
      "CreatedOrModified": "2023-08-01 00:34:30",
      "Comment": "",
      "Prompt": {
        "Prompt Text": "Start listening. What's today's news?",
        "Transcript": "Start listening. What's today's news?",
        "Category Description": "Digital Assistant Commands",
        "Sub Category Description": "News, weather, traffic"
      }
    },
    {
      "Filename": "7ad56daf-964e-4c64-9994-e9990a154cec_42_8080.wav",
      "CreatedOrModified": "2024-02-09 19:25:21",
      "Comment": "",
      "Prompt": {
        "Prompt Text": "What song is this?",
        "Transcript": "What song is this?",
        "Category Description": "Digital Assistant Commands",
        "Sub Category Description": "Media control"
      }
    },
    {
      "Filename": "7ad56daf-964e-4c64-9994-e9990a154cec_95_2004.wav",
      "CreatedOrModified": "2023-11-22 15:09:00",
      "Comment": "",
      "Prompt": {
        "Prompt Text": "Listen to Bloomberg.",
        "Transcript": "Listen to Bloomberg.",
        "Category Description": "Digital Assistant Commands",
        "Sub Category Description": "News, weather, traffic"
      }
    },
    {
      "Filename": "7ad56daf-964e-4c64-9994-e9990a154cec_86_7165.wav",
      "CreatedOrModified": "2023-04-03 16:55:51",
      "Comment": "",
      "Prompt": {
        "Prompt Text": "When are the Nashville Predators playing next?",
        "Transcript": "When are the Nashville Predators playing next?",
        "Category Description": "Digital Assistant Commands",
        "Sub Category Description": "News, weather, traffic"
      }
    },
    {
      "Filename": "7ad56daf-964e-4c64-9994-e9990a154cec_99_8770.wav",
      "CreatedOrModified": "2023-06-01 07:09:17",
      "Comment": "",
      "Prompt": {
        "Prompt Text": "When does the next train arrive?",
        "Transcript": "When does the next train arrive?",
        "Category Description": "Digital Assistant Commands",
        "Sub Category Description": "News, weather, traffic"
      }
    },
    {
      "Filename": "7ad56daf-964e-4c64-9994-e9990a154cec_62_4962.wav",
      "CreatedOrModified": "2024-02-19 04:27:46",
      "Comment": "",
      "Prompt": {
        "Prompt Text": "Set an alarm for 6:30 PM Daily.",
        "Transcript": "Set an alarm for 6:30 PM Daily.",
        "Category Description": "Digital Assistant Commands",
        "Sub Category Description": "Tasks and planning"
      }
    },
    {
      "Filename": "7ad56daf-964e-4c64-9994-e9990a154cec_81_1382.wav",
      "CreatedOrModified": "2023-09-09 20:27:38",
      "Comment": "",
      "Prompt": {
        "Prompt Text": "How far is Shanghai, China from Beijing, China?",
        "Transcript": "How far is Shanghai, China from Beijing, China?",
        "Category Description": "Digital Assistant Commands",
        "Sub Category Description": "News, weather, traffic"
      }
    },
    {
      "Filename": "7ad56daf-964e-4c64-9994-e9990a154cec_55_5066.wav",
      "CreatedOrModified": "2023-10-09 07:36:15",
      "Comment": "",
      "Prompt": {
        "Prompt Text": "Set a reminder to take pantoprazole at 6 AM.",
        "Transcript": "Set a reminder to take pantoprazole at 6 AM.",
        "Category Description": "Digital Assistant Commands",
        "Sub Category Description": "Tasks and planning"
      }
    },
    {
      "Filename": "7ad56daf-964e-4c64-9994-e9990a154cec_46_4981.wav",
      "CreatedOrModified": "2023-10-23 06:51:22",
      "Comment": "",
      "Prompt": {
        "Prompt Text": "Get help.",
        "Transcript": "Get help.",
        "Category Description": "Digital Assistant Commands",
        "Sub Category Description": "Phone"
      }
    },
    {
      "Filename": "7ad56daf-964e-4c64-9994-e9990a154cec_42_7569.wav",
      "CreatedOrModified": "2023-10-30 11:20:08",
      "Comment": "",
      "Prompt": {
        "Prompt Text": "Is the nearest movie theater ADA compliant?",
        "Transcript": "Is the nearest movie theater ADA compliant?",
        "Category Description": "Digital Assistant Commands",
        "Sub Category Description": "Online Search"
      }
    },
    {
      "Filename": "7ad56daf-964e-4c64-9994-e9990a154cec_33_6868.wav",
      "CreatedOrModified": "2023-11-23 00:02:11",
      "Comment": "",
      "Prompt": {
        "Prompt Text": "Who played third base for the Pittsburgh Pirates in 1960? ",
        "Transcript": "Who played third base for the Pittsburgh Pirates in 1960? ",
        "Category Description": "Digital Assistant Commands",
        "Sub Category Description": "Online Search"
      }
    },
    {
      "Filename": "7ad56daf-964e-4c64-9994-e9990a154cec_93_5108.wav",
      "CreatedOrModified": "2023-09-02 21:54:05",
      "Comment": "",
      "Prompt": {
        "Prompt Text": "Hey Siri, pause the music.",
        "Transcript": "Hey Siri, pause the eovr music.",
        "Category Description": "Digital Assistant Commands",
        "Sub Category Description": "Media control"
      }
    }
  ]
}